chrofile/__init__.py
chrofile/_version.py
chrofile/cli.py
chrofile/consts.py
chrofile/core.py
chrofile-0.0.11.dist-info/LICENSE.txt
chrofile-0.0.11.dist-info/METADATA
chrofile-0.0.11.dist-info/WHEEL
chrofile-0.0.11.dist-info/top_level.txt
chrofile-0.0.11.dist-info/RECORD
