Metadata-Version: 2.1
Name: chrofile
Version: 0.0.11
Summary: chrome profile setting tool
Home-page: https://github.com/inouve/chrofile
Author: inovue
Author-email: info@sinoue.net
Project-URL: Bug Tracker, https://github.com/inouve/chrofile
Classifier: Programming Language :: Python :: 3
Classifier: License :: OSI Approved :: MIT License
Classifier: Operating System :: OS Independent
Requires-Python: >=3.6
License-File: LICENSE.txt
